{"success":true,"data":
{"coord":{"lon":-93.2938,"lat":45.8769},"weather":[{"id":701,"main":"Mist","description":"mist","icon":"50d"}],"base":"stations","main":{"temp":21.2,"feels_like":10.13,"temp_min":21.18,"temp_max":21.45,"pressure":1011,"humidity":87,"sea_level":1011,"grnd_level":971},"visibility":8047,"wind":{"speed":10.36,"deg":110,"gust":16.11},"clouds":{"all":100},"dt":1767556066,"sys":{"type":1,"id":4596,"country":"US","sunrise":1767534869,"sunset":1767566488},"timezone":-21600,"id":5038195,"name":"Mora","cod":200},"cached":false,"timestamp":"2026-01-04T19:47:46Z","source":"GitHub Actions"}
